prismor/__init__.py
prismor/api.py
prismor/cli.py
prismor-0.1.0.dist-info/licenses/LICENSE
prismor-0.1.0.dist-info/METADATA
prismor-0.1.0.dist-info/WHEEL
prismor-0.1.0.dist-info/entry_points.txt
prismor-0.1.0.dist-info/top_level.txt
prismor-0.1.0.dist-info/RECORD
