Metadata-Version: 2.4
Name: prismor
Version: 0.1.0
Summary: A CLI tool for scanning GitHub repositories for vulnerabilities, secrets, and generating SBOMs
Home-page: https://github.com/PrismorSec/prismor-cli
Author: Prismor
Author-email: support@prismor.dev
Project-URL: Bug Reports, https://github.com/PrismorSec/prismor-cli/issues
Project-URL: Source, https://github.com/PrismorSec/prismor-cli
Project-URL: Documentation, https://docs.prismor.dev
Project-URL: Homepage, https://prismor.dev
Keywords: security scanning vulnerability sbom secrets github
Classifier: Development Status :: 4 - Beta
Classifier: Intended Audience :: Developers
Classifier: Topic :: Security
Classifier: Topic :: Software Development :: Quality Assurance
Classifier: License :: OSI Approved :: MIT License
Classifier: Programming Language :: Python :: 3
Classifier: Programming Language :: Python :: 3.7
Classifier: Programming Language :: Python :: 3.8
Classifier: Programming Language :: Python :: 3.9
Classifier: Programming Language :: Python :: 3.10
Classifier: Programming Language :: Python :: 3.11
Classifier: Programming Language :: Python :: 3.12
Requires-Python: >=3.7
License-File: LICENSE
Requires-Dist: click>=8.0.0
Requires-Dist: requests>=2.25.0
Dynamic: author
Dynamic: author-email
Dynamic: classifier
Dynamic: description
Dynamic: description-content-type
Dynamic: home-page
Dynamic: keywords
Dynamic: license-file
Dynamic: project-url
Dynamic: requires-dist
Dynamic: requires-python
Dynamic: summary
